{
    "filename": "destroy-1.20.1-0.8.jar",
    "side": "both",
    "hashes": {
        "sha1": "b528cdcb0aa21370e92127442a320ebe37dbb0eb",
        "sha512": "96168c056240822ad3c107a8530b2e7ecf8b1ceea8cce293adf8610a0c343e116dc060809fba473b6a03360c87865571be65f60b44705ed0331c08a76f761f12",
        "murmur2": 3233600913
    },
    "fileSize": 7771775,
    "sources": {
        "curseforge": {
            "projectId": 656356,
            "fileUrl": "https://edge.forgecdn.net/files/5103/248/destroy-1.20.1-0.8.jar",
            "fileId": 5103248
        },
        "modrinth": {
            "projectId": "uY7EYHum",
            "fileUrl": "https://cdn.modrinth.com/data/uY7EYHum/versions/glM7hO6V/destroy-1.20.1-0.8.jar"
        }
    }
}
